MANIFEST.in
configure.py
license
setup.cfg
setup.py
/home/scopatz/xdress/scripts/xdress
/home/scopatz/xdress/xdress/clang/src/ARCMigrate.cpp
/home/scopatz/xdress/xdress/clang/src/CIndex.cpp
/home/scopatz/xdress/xdress/clang/src/CIndexCXX.cpp
/home/scopatz/xdress/xdress/clang/src/CIndexCodeCompletion.cpp
/home/scopatz/xdress/xdress/clang/src/CIndexDiagnostic.cpp
/home/scopatz/xdress/xdress/clang/src/CIndexHigh.cpp
/home/scopatz/xdress/xdress/clang/src/CIndexInclusionStack.cpp
/home/scopatz/xdress/xdress/clang/src/CIndexUSRs.cpp
/home/scopatz/xdress/xdress/clang/src/CIndexer.cpp
/home/scopatz/xdress/xdress/clang/src/CXComment.cpp
/home/scopatz/xdress/xdress/clang/src/CXCompilationDatabase.cpp
/home/scopatz/xdress/xdress/clang/src/CXCursor.cpp
/home/scopatz/xdress/xdress/clang/src/CXLoadedDiagnostic.cpp
/home/scopatz/xdress/xdress/clang/src/CXSourceLocation.cpp
/home/scopatz/xdress/xdress/clang/src/CXStoredDiagnostic.cpp
/home/scopatz/xdress/xdress/clang/src/CXString.cpp
/home/scopatz/xdress/xdress/clang/src/CXType.cpp
/home/scopatz/xdress/xdress/clang/src/IndexBody.cpp
/home/scopatz/xdress/xdress/clang/src/IndexDecl.cpp
/home/scopatz/xdress/xdress/clang/src/IndexTypeSourceInfo.cpp
/home/scopatz/xdress/xdress/clang/src/Indexing.cpp
/home/scopatz/xdress/xdress/clang/src/IndexingContext.cpp
/home/scopatz/xdress/xdress/clang/src/xdress-clang.cpp
docs/index.rst
scripts/xdress
scripts/xdress.bat
xdress/__init__.py
xdress/astparsers.py
xdress/autoall.py
xdress/autodescribe.py
xdress/base.py
xdress/cythongen.py
xdress/descfilter.py
xdress/doxygen.py
xdress/dtypes.py
xdress/extratypes.py
xdress/main.py
xdress/pep8names.py
xdress/plugins.py
xdress/stlwrap.py
xdress/typesystem.py
xdress/utils.py
xdress/version.py
xdress/xdress_extra_types.h
xdress/xdress_extra_types.pxd
xdress/xdress_extra_types.pyx
xdress.egg-info/PKG-INFO
xdress.egg-info/SOURCES.txt
xdress.egg-info/dependency_links.txt
xdress.egg-info/top_level.txt
xdress/_enum/LICENSE
xdress/_enum/README
xdress/_enum/__init__.py
xdress/_enum/enum.py
xdress/_enum/test_enum.py
xdress/clang/__init__.py
xdress/clang/cindex.py
