Metadata-Version: 1.1
Name: xdress
Version: 0.4
Summary: Goes all J. Edgar Hoover on your code.
Home-page: http://xdress.org/
Author: Anthony Scopatz
Author-email: xdress@googlegroups.com
License: UNKNOWN
Download-URL: https://github.com/scopatz/xdress/zipball/0..
Platform: UNKNOWN
Classifier: License :: OSI Approved :: BSD License
Classifier: Intended Audience :: Developers
Classifier: Intended Audience :: Science/Research
Classifier: Programming Language :: C
Classifier: Programming Language :: C++
Classifier: Programming Language :: Cython
Classifier: Programming Language :: Python :: 2
Classifier: Programming Language :: Python :: 3
Classifier: Programming Language :: Python :: Implementation :: CPython
Classifier: Topic :: Scientific/Engineering
Classifier: Topic :: Software Development :: Code Generators
Classifier: Topic :: Software Development :: Compilers
Classifier: Topic :: Utilities
